[
  {
    "id": 1744487540044,
    "task": "вава"
  },
  {
    "id": 1744474613546,
    "task": "1ну прикольно нейронки мутят",
    "completed": true
  },
  {
    "id": 1744403185168,
    "task": "дада"
  },
  {
    "id": 1744403182842,
    "task": "круто2",
    "completed": false
  },
  {
    "id": 1744403177591,
    "task": "есть круть",
    "completed": false
  },
  {
    "id": 1744474620256,
    "task": "прям  тема"
  },
  {
    "id": 1744474653654,
    "task": "ждж"
  },
  {
    "id": 1744474622548,
    "task": "еще да"
  },
  {
    "id": 1744474623881,
    "task": "тут"
  },
  {
    "id": 1744474882342,
    "task": "ХЪъъхХХХ{{}}[[//"
  }
]